naomi_paginator/__init__.py
naomi_paginator-1.3.1.dist-info/LICENSE
naomi_paginator-1.3.1.dist-info/METADATA
naomi_paginator-1.3.1.dist-info/WHEEL
naomi_paginator-1.3.1.dist-info/top_level.txt
naomi_paginator-1.3.1.dist-info/RECORD
