Metadata-Version: 2.1
Name: naomi-paginator
Version: 1.3.1
Summary: Simple Embed paginator written in Python for discord.py bots
Home-page: https://github.com/The-Naomi-Developers/naomi-paginator
Author: The-Naomi-Developers
License: MIT
Platform: UNKNOWN
Classifier: Programming Language :: Python :: 3
Classifier: Programming Language :: Python :: 3.6
Classifier: Programming Language :: Python :: 3.7
Classifier: Programming Language :: Python :: 3.8
Requires-Dist: discord.py
